{
    "type": "FeatureCollection",
    "features": [
        {
            "type": "Feature",
            "id": "node/-4284",
            "properties": {
                "amenity": "kindergarten",
                "capacity": "40",
                "contact:email": "ingebjorg.breisnes@leikanger.kommune.no",
                "max_age": "5",
                "min_age": "1",
                "name": "Nybø barnehage",
                "no-barnehage:nsrid": "1012513",
                "operator": "Leikanger kommune",
                "operator:type": "public",
                "start_date": "1989-01-01",
                "id": "node/-4284"
            },
            "geometry": {
                "type": "Point",
                "coordinates": [
                    6.83278,
                    61.1861
                ]
            }
        },
        {
            "type": "Feature",
            "id": "node/-4283",
            "properties": {
                "amenity": "kindergarten",
                "capacity": "44",
                "contact:email": "maj.sissel.olnes@leikanger.kommune.no",
                "max_age": "5",
                "min_age": "1",
                "name": "Henjahaugane barnehage",
                "no-barnehage:nsrid": "1013965",
                "operator": "Leikanger kommune",
                "operator:type": "public",
                "start_date": "1991-01-01",
                "id": "node/-4283"
            },
            "geometry": {
                "type": "Point",
                "coordinates": [
                    6.84261,
                    61.1897
                ]
            }
        }
    ]
}