{
    "type": "FeatureCollection",
    "features": [
        {
            "type": "Feature",
            "id": "node/-5106",
            "properties": {
                "amenity": "kindergarten",
                "capacity": "35",
                "contact:email": "lyngen@mobarn.no",
                "contact:phone": "+47 91653623",
                "doNotImportAddress": "Åndalsbakken 7 6409 MOLDE",
                "max_age": "5",
                "min_age": "1",
                "name": "Mobarn Lyngen barnehage",
                "no-barnehage:nsrid": "2000054",
                "operator": "Mobarn Sa",
                "operator:type": "private",
                "id": "node/-5106"
            },
            "geometry": {
                "type": "Point",
                "coordinates": [
                    7.022853,
                    62.78901
                ]
            }
        },
        {
            "type": "Feature",
            "id": "node/-5102",
            "properties": {
                "amenity": "kindergarten",
                "capacity": "41",
                "contact:email": "elin.jendem.barnehage@frenabb.no",
                "contact:phone": "+47 71 26 03 70",
                "doNotImportAddress": "Storelvvegen 19 6409 MOLDE",
                "max_age": "5",
                "min_age": "1",
                "name": "Jendem barnehage",
                "no-barnehage:nsrid": "1021068",
                "operator": "Jendem Velforening",
                "operator:type": "private",
                "id": "node/-5102"
            },
            "geometry": {
                "type": "Point",
                "coordinates": [
                    7.007379,
                    62.78763
                ]
            }
        }
    ]
}