{
    "type": "FeatureCollection",
    "features": [
        {
            "type": "Feature",
            "id": "node/-2976",
            "properties": {
                "amenity": "kindergarten",
                "capacity": "120",
                "max_age": "5",
                "min_age": "1",
                "name": "Skinsnesheia barnehage",
                "no-barnehage:nsrid": "1021160",
                "operator": "Skinsnesheia barnehage AS",
                "operator:type": "private",
                "id": "node/-2976"
            },
            "geometry": {
                "type": "Point",
                "coordinates": [
                    7.486829,
                    58.02808
                ]
            }
        },
        {
            "type": "Feature",
            "id": "node/-2975",
            "properties": {
                "amenity": "kindergarten",
                "capacity": "15",
                "max_age": "5",
                "min_age": "1",
                "name": "Rauneveien barnehage",
                "no-barnehage:nsrid": "1022359",
                "operator": "Rauneveien barnehage AS",
                "operator:type": "private",
                "id": "node/-2975"
            },
            "geometry": {
                "type": "Point",
                "coordinates": [
                    7.491377,
                    58.02916
                ]
            }
        }
    ]
}