{
    "type": "FeatureCollection",
    "features": [
        {
            "type": "Feature",
            "id": "node/-4314",
            "properties": {
                "amenity": "kindergarten",
                "capacity": "12",
                "contact:email": "jenny.gerd.lioen@laerdal.kommune.no",
                "max_age": "5",
                "min_age": "1",
                "name": "Borgund barnehage",
                "no-barnehage:nsrid": "1012514",
                "operator": "Lærdal kommune",
                "operator:type": "public",
                "start_date": "1989-01-01",
                "id": "node/-4314"
            },
            "geometry": {
                "type": "Point",
                "coordinates": [
                    7.77049,
                    61.0528
                ]
            }
        }
    ]
}