{
    "type": "FeatureCollection",
    "features": [
        {
            "type": "Feature",
            "id": "node/-3665",
            "properties": {
                "amenity": "kindergarten",
                "capacity": "33",
                "contact:email": "ovrebobarnehage@gmail.com",
                "doNotImportAddress": "Lolandsvegen 37 4715 ØVREBØ",
                "max_age": "5",
                "min_age": "1",
                "name": "Øverbø Opplæringskontor",
                "no-barnehage:nsrid": "1020565",
                "operator": "Øvrebø Opplæringskontor AS",
                "operator:type": "private",
                "id": "node/-3665"
            },
            "geometry": {
                "type": "Point",
                "coordinates": [
                    7.777582,
                    58.29074
                ]
            }
        }
    ]
}