{
    "type": "FeatureCollection",
    "features": [
        {
            "type": "Feature",
            "id": "node/-3571",
            "properties": {
                "amenity": "kindergarten",
                "capacity": "53",
                "contact:email": "solveig.m.voie@kristiansand.kommune.no",
                "contact:phone": "+47 38 10 34 90",
                "max_age": "5",
                "min_age": "1",
                "name": "Taremareskogen barnehage",
                "no-barnehage:nsrid": "1016058",
                "operator": "Kristiansand kommune",
                "operator:type": "public",
                "id": "node/-3571"
            },
            "geometry": {
                "type": "Point",
                "coordinates": [
                    8.00048,
                    58.0858
                ]
            }
        }
    ]
}