{
    "type": "FeatureCollection",
    "features": [
        {
            "type": "Feature",
            "id": "node/-5362",
            "properties": {
                "ADDRESS": "Podeveien 12, 3770 KRAGERØ",
                "amenity": "kindergarten",
                "capacity": "29",
                "max_age": "5",
                "min_age": "1",
                "name": "Solsikke barnehage",
                "no-barnehage:nsrid": "1020272",
                "operator": "Stiftelsen Solsikke barnehage",
                "operator:type": "private",
                "id": "node/-5362"
            },
            "geometry": {
                "type": "Point",
                "coordinates": [
                    9.39285,
                    58.8838
                ]
            }
        },
        {
            "type": "Feature",
            "id": "node/-5356",
            "properties": {
                "ADDRESS": "Rådyrveien 16a, 3790 HELLE",
                "amenity": "kindergarten",
                "capacity": "41",
                "max_age": "5",
                "min_age": "1",
                "name": "Hellekirken barnehage",
                "no-barnehage:nsrid": "1015647",
                "operator": "Kragerø kommune",
                "operator:type": "public",
                "id": "node/-5356"
            },
            "geometry": {
                "type": "Point",
                "coordinates": [
                    9.37025,
                    58.89868
                ]
            }
        }
    ]
}