{
    "type": "FeatureCollection",
    "features": [
        {
            "type": "Feature",
            "id": "node/-2761",
            "properties": {
                "amenity": "kindergarten",
                "capacity": "83",
                "contact:email": "cathrine.braathen@bamble.kommune.no",
                "contact:phone": "+47 35 97 38 66",
                "doNotImportAddress": "Øvre Nustadvei 10 3970 LANGESUND",
                "max_age": "5",
                "min_age": "1",
                "name": "Nustad barnehage",
                "no-barnehage:nsrid": "1018041",
                "operator": "Bamble kommune",
                "operator:type": "public",
                "id": "node/-2761"
            },
            "geometry": {
                "type": "Point",
                "coordinates": [
                    9.72885,
                    59.0108
                ]
            }
        }
    ]
}