{
    "type": "FeatureCollection",
    "features": [
        {
            "type": "Feature",
            "id": "node/-2353",
            "properties": {
                "ADDRESS": "Ottersboveien 50, 7140 OPPHAUG",
                "amenity": "kindergarten",
                "capacity": "44",
                "contact:website": "http://www.orland.kommune.no",
                "max_age": "5",
                "min_age": "1",
                "name": "Borgen barnehage",
                "no-barnehage:nsrid": "1014686",
                "operator": "Ørland kommune",
                "operator:type": "public",
                "id": "node/-2353"
            },
            "geometry": {
                "type": "Point",
                "coordinates": [
                    9.76491,
                    63.70943
                ]
            }
        }
    ]
}