{
    "type": "FeatureCollection",
    "features": [
        {
            "type": "Feature",
            "id": "node/-3708",
            "properties": {
                "ADDRESS": "Trøaveien 12, 7105 STADSBYGD",
                "amenity": "kindergarten",
                "capacity": "29",
                "max_age": "5",
                "min_age": "1",
                "name": "Tungtrø barnehage",
                "no-barnehage:nsrid": "1022197",
                "operator": "Tungtrø barnehage AS",
                "operator:type": "private",
                "id": "node/-3708"
            },
            "geometry": {
                "type": "Point",
                "coordinates": [
                    10.01634,
                    63.50935
                ]
            }
        },
        {
            "type": "Feature",
            "id": "node/-3699",
            "properties": {
                "ADDRESS": "Valsåmyra 22, 7105 STADSBYGD",
                "amenity": "kindergarten",
                "capacity": "55",
                "contact:website": "http://www.indrefosen.kommune.no",
                "max_age": "5",
                "min_age": "1",
                "name": "Fembøringen barnehage",
                "no-barnehage:nsrid": "1016114",
                "operator": "Indre Fosen kommune",
                "operator:type": "public",
                "id": "node/-3699"
            },
            "geometry": {
                "type": "Point",
                "coordinates": [
                    10.01893,
                    63.50797
                ]
            }
        }
    ]
}