{
    "type": "FeatureCollection",
    "features": [
        {
            "type": "Feature",
            "id": "node/-1885",
            "properties": {
                "amenity": "kindergarten",
                "capacity": "65",
                "max_age": "5",
                "min_age": "1",
                "name": "Kroka barnehage",
                "no-barnehage:nsrid": "1015827",
                "operator": "Modum kommune",
                "operator:type": "public",
                "id": "node/-1885"
            },
            "geometry": {
                "type": "Point",
                "coordinates": [
                    9.98054,
                    59.9589
                ]
            }
        },
        {
            "type": "Feature",
            "id": "node/-1877",
            "properties": {
                "amenity": "kindergarten",
                "capacity": "50",
                "max_age": "5",
                "min_age": "1",
                "name": "Barnas Hus",
                "no-barnehage:nsrid": "1018014",
                "operator": "Modum kommune",
                "operator:type": "public",
                "id": "node/-1877"
            },
            "geometry": {
                "type": "Point",
                "coordinates": [
                    9.99252,
                    59.9667
                ]
            }
        }
    ]
}