{
    "type": "FeatureCollection",
    "features": [
        {
            "type": "Feature",
            "id": "node/-2896",
            "properties": {
                "ADDRESS": "Olaf Grilstads Veg 1, 7025 TRONDHEIM",
                "amenity": "kindergarten",
                "capacity": "67",
                "max_age": "5",
                "min_age": "1",
                "name": "Myra barnehage",
                "no-barnehage:nsrid": "1016737",
                "operator": "Trondheim kommune",
                "operator:type": "public",
                "id": "node/-2896"
            },
            "geometry": {
                "type": "Point",
                "coordinates": [
                    10.33802,
                    63.40338
                ]
            }
        },
        {
            "type": "Feature",
            "id": "node/-2887",
            "properties": {
                "ADDRESS": "Inge Krokanns Veg 3, 7071 TRONDHEIM",
                "amenity": "kindergarten",
                "capacity": "53",
                "max_age": "5",
                "min_age": "1",
                "name": "Kystadåsen barnehage",
                "no-barnehage:nsrid": "1018215",
                "operator": "Trondheim kommune",
                "operator:type": "public",
                "id": "node/-2887"
            },
            "geometry": {
                "type": "Point",
                "coordinates": [
                    10.32966,
                    63.39644
                ]
            }
        }
    ]
}