{
    "type": "FeatureCollection",
    "features": [
        {
            "type": "Feature",
            "id": "node/-1077",
            "properties": {
                "ADDRESS": "Åkebergveien 23, 0650 OSLO",
                "amenity": "kindergarten",
                "capacity": "99",
                "max_age": "5",
                "min_age": "1",
                "name": "Åkeberg barnehage",
                "no-barnehage:nsrid": "1017322",
                "operator": "Oslo kommune",
                "operator:type": "public",
                "id": "node/-1077"
            },
            "geometry": {
                "type": "Point",
                "coordinates": [
                    10.77815,
                    59.90819
                ]
            }
        },
        {
            "type": "Feature",
            "id": "node/-1066",
            "properties": {
                "ADDRESS": "Vårveien 1d, 1182 OSLO",
                "amenity": "kindergarten",
                "capacity": "90",
                "max_age": "5",
                "min_age": "1",
                "name": "Vårveien barnehage",
                "no-barnehage:nsrid": "1013255",
                "operator": "Oslo kommune",
                "operator:type": "public",
                "id": "node/-1066"
            },
            "geometry": {
                "type": "Point",
                "coordinates": [
                    10.78824,
                    59.89585
                ]
            }
        },
        {
            "type": "Feature",
            "id": "node/-1041",
            "properties": {
                "ADDRESS": "Utsikten 10, 0196 OSLO",
                "amenity": "kindergarten",
                "capacity": "11",
                "max_age": "5",
                "min_age": "1",
                "name": "Utsikten barnehage",
                "no-barnehage:nsrid": "1016837",
                "operator": "Oslo kommune",
                "operator:type": "public",
                "id": "node/-1041"
            },
            "geometry": {
                "type": "Point",
                "coordinates": [
                    10.78216,
                    59.9011
                ]
            }
        },
        {
            "type": "Feature",
            "id": "node/-978",
            "properties": {
                "ADDRESS": "Enebakkveien 152b, 0680 OSLO",
                "amenity": "kindergarten",
                "capacity": "68",
                "max_age": "5",
                "min_age": "1",
                "name": "Svartdalsparken Kanvas-barnehage",
                "no-barnehage:nsrid": "1015483",
                "operator": "Stiftelsen Kanvas",
                "operator:type": "private",
                "id": "node/-978"
            },
            "geometry": {
                "type": "Point",
                "coordinates": [
                    10.80225,
                    59.89784
                ]
            }
        },
        {
            "type": "Feature",
            "id": "node/-958",
            "properties": {
                "ADDRESS": "Byggveien 9, 0680 OSLO",
                "amenity": "kindergarten",
                "capacity": "136",
                "max_age": "5",
                "min_age": "1",
                "name": "Storgården barnehage",
                "no-barnehage:nsrid": "1017316",
                "operator": "Oslo kommune",
                "operator:type": "public",
                "id": "node/-958"
            },
            "geometry": {
                "type": "Point",
                "coordinates": [
                    10.80866,
                    59.89531
                ]
            }
        },
        {
            "type": "Feature",
            "id": "node/-940",
            "properties": {
                "ADDRESS": "Vålerenggata 27, 0658 OSLO",
                "amenity": "kindergarten",
                "capacity": "32",
                "max_age": "5",
                "min_age": "1",
                "name": "Sotamyggen barnehage",
                "no-barnehage:nsrid": "1018525",
                "operator": "Oslo kommune",
                "operator:type": "public",
                "id": "node/-940"
            },
            "geometry": {
                "type": "Point",
                "coordinates": [
                    10.78747,
                    59.90819
                ]
            }
        },
        {
            "type": "Feature",
            "id": "node/-878",
            "properties": {
                "ADDRESS": "Solfjellshøgda 28, 0677 OSLO",
                "amenity": "kindergarten",
                "capacity": "69",
                "max_age": "5",
                "min_age": "1",
                "name": "Rygin barnehage",
                "no-barnehage:nsrid": "1013821",
                "operator": "Oslo kommune",
                "operator:type": "public",
                "id": "node/-878"
            },
            "geometry": {
                "type": "Point",
                "coordinates": [
                    10.79963,
                    59.89932
                ]
            }
        },
        {
            "type": "Feature",
            "id": "node/-818",
            "properties": {
                "ADDRESS": "Opplandsgate 5, 0657 OSLO",
                "amenity": "kindergarten",
                "capacity": "34",
                "max_age": "5",
                "min_age": "1",
                "name": "Norlandia Enga barnehage",
                "no-barnehage:nsrid": "1015041",
                "operator": "Norlandia Barnehagene AS",
                "operator:type": "private",
                "id": "node/-818"
            },
            "geometry": {
                "type": "Point",
                "coordinates": [
                    10.78506,
                    59.90735
                ]
            }
        },
        {
            "type": "Feature",
            "id": "node/-802",
            "properties": {
                "ADDRESS": "Grønlandsleiret 71, 0190 OSLO",
                "amenity": "kindergarten",
                "capacity": "68",
                "contact:website": "http://laringsverkstedet.no",
                "max_age": "5",
                "min_age": "1",
                "name": "Nonneseter Kloster idrettsbarnehage",
                "no-barnehage:nsrid": "1022365",
                "operator": "Nonneseter Kloster barnehage AS",
                "operator:type": "private",
                "id": "node/-802"
            },
            "geometry": {
                "type": "Point",
                "coordinates": [
                    10.76822,
                    59.90935
                ]
            }
        },
        {
            "type": "Feature",
            "id": "node/-784",
            "properties": {
                "ADDRESS": "Galgeberg 2, 0657 OSLO",
                "amenity": "kindergarten",
                "capacity": "60",
                "max_age": "5",
                "min_age": "1",
                "name": "Munkenga barnehage",
                "no-barnehage:nsrid": "1013279",
                "operator": "Oslo kommune",
                "operator:type": "public",
                "id": "node/-784"
            },
            "geometry": {
                "type": "Point",
                "coordinates": [
                    10.77866,
                    59.90757
                ]
            }
        },
        {
            "type": "Feature",
            "id": "node/-781",
            "properties": {
                "ADDRESS": "Totengata 7, 0658 OSLO",
                "amenity": "kindergarten",
                "capacity": "21",
                "max_age": "5",
                "min_age": "1",
                "name": "Munik barnehage Karin Jacobsen",
                "no-barnehage:nsrid": "1019948",
                "operator": "Munik barnehage Karin Jacobsen",
                "operator:type": "private",
                "id": "node/-781"
            },
            "geometry": {
                "type": "Point",
                "coordinates": [
                    10.78789,
                    59.90962
                ]
            }
        },
        {
            "type": "Feature",
            "id": "node/-749",
            "properties": {
                "ADDRESS": "Magnefaret 13b, 0678 OSLO",
                "amenity": "kindergarten",
                "capacity": "67",
                "max_age": "5",
                "min_age": "1",
                "name": "Manglerud barnehage",
                "no-barnehage:nsrid": "1017299",
                "operator": "Oslo kommune",
                "operator:type": "public",
                "id": "node/-749"
            },
            "geometry": {
                "type": "Point",
                "coordinates": [
                    10.80492,
                    59.90121
                ]
            }
        },
        {
            "type": "Feature",
            "id": "node/-685",
            "properties": {
                "ADDRESS": "Barnehjemsveien 2, 1181 OSLO",
                "amenity": "kindergarten",
                "capacity": "135",
                "max_age": "5",
                "min_age": "1",
                "name": "Lille Ekeberg barnehage",
                "no-barnehage:nsrid": "1017298",
                "operator": "Oslo kommune",
                "operator:type": "public",
                "id": "node/-685"
            },
            "geometry": {
                "type": "Point",
                "coordinates": [
                    10.78608,
                    59.8982
                ]
            }
        },
        {
            "type": "Feature",
            "id": "node/-673",
            "properties": {
                "ADDRESS": "Enebakkveien 71b, 0196 OSLO",
                "amenity": "kindergarten",
                "capacity": "374",
                "max_age": "5",
                "min_age": "1",
                "name": "Kværnerdalen barnehage",
                "no-barnehage:nsrid": "1018609",
                "operator": "Oslo kommune",
                "operator:type": "public",
                "id": "node/-673"
            },
            "geometry": {
                "type": "Point",
                "coordinates": [
                    10.79138,
                    59.90307
                ]
            }
        },
        {
            "type": "Feature",
            "id": "node/-672",
            "properties": {
                "ADDRESS": "Turbinveien 32, 0195 OSLO",
                "amenity": "kindergarten",
                "capacity": "78",
                "max_age": "5",
                "min_age": "1",
                "name": "Kværnerbyen FUS barnehage",
                "no-barnehage:nsrid": "1021723",
                "operator": "Kværnerbyen Fus barnehage AS",
                "operator:type": "private",
                "id": "node/-672"
            },
            "geometry": {
                "type": "Point",
                "coordinates": [
                    10.78868,
                    59.90305
                ]
            }
        },
        {
            "type": "Feature",
            "id": "node/-634",
            "properties": {
                "ADDRESS": "Jordalgata 11, 0657 OSLO",
                "amenity": "kindergarten",
                "capacity": "52",
                "max_age": "5",
                "min_age": "1",
                "name": "Jordal barnehage",
                "no-barnehage:nsrid": "1013823",
                "operator": "Oslo kommune",
                "operator:type": "public",
                "id": "node/-634"
            },
            "geometry": {
                "type": "Point",
                "coordinates": [
                    10.78536,
                    59.90891
                ]
            }
        },
        {
            "type": "Feature",
            "id": "node/-629",
            "properties": {
                "ADDRESS": "Åkebergveien 23, 0650 OSLO",
                "amenity": "kindergarten",
                "capacity": "41",
                "contact:website": "http://www.internasjonalkulturbarnehage.no",
                "max_age": "5",
                "min_age": "1",
                "name": "Internasjonal kultur barnehage Åkeberg",
                "no-barnehage:nsrid": "1013090",
                "operator": "Internasjonal Kultur barnehage Ingeborg Helene Aanonsen",
                "operator:type": "private",
                "id": "node/-629"
            },
            "geometry": {
                "type": "Point",
                "coordinates": [
                    10.77815,
                    59.90819
                ]
            }
        },
        {
            "type": "Feature",
            "id": "node/-628",
            "properties": {
                "ADDRESS": "Enebakkveien 22, 0657 OSLO",
                "amenity": "kindergarten",
                "capacity": "27",
                "contact:website": "http://www.internasjonalkulturbarnehage.no",
                "max_age": "2",
                "min_age": "1",
                "name": "Internasjonal kultur barnehage Enebakkveien",
                "no-barnehage:nsrid": "1016547",
                "operator": "Internasjonal Kultur barnehage Ingeborg Helene Aanonsen",
                "operator:type": "private",
                "id": "node/-628"
            },
            "geometry": {
                "type": "Point",
                "coordinates": [
                    10.78281,
                    59.90691
                ]
            }
        },
        {
            "type": "Feature",
            "id": "node/-624",
            "properties": {
                "ADDRESS": "Manglebergveien 9, 0678 OSLO",
                "amenity": "kindergarten",
                "capacity": "80",
                "max_age": "5",
                "min_age": "1",
                "name": "Husmannsplassen barnehage",
                "no-barnehage:nsrid": "1013479",
                "operator": "Oslo kommune",
                "operator:type": "public",
                "id": "node/-624"
            },
            "geometry": {
                "type": "Point",
                "coordinates": [
                    10.80917,
                    59.90046
                ]
            }
        },
        {
            "type": "Feature",
            "id": "node/-621",
            "properties": {
                "ADDRESS": "Hurdalsgata 6, 0655 OSLO",
                "amenity": "kindergarten",
                "capacity": "28",
                "max_age": "5",
                "min_age": "1",
                "name": "Hurdalsgata barnehage",
                "no-barnehage:nsrid": "1013825",
                "operator": "Oslo kommune",
                "operator:type": "public",
                "id": "node/-621"
            },
            "geometry": {
                "type": "Point",
                "coordinates": [
                    10.78099,
                    59.90988
                ]
            }
        },
        {
            "type": "Feature",
            "id": "node/-535",
            "properties": {
                "ADDRESS": "Oslo Gate 17-21, 0192 OSLO",
                "amenity": "kindergarten",
                "capacity": "72",
                "max_age": "5",
                "min_age": "1",
                "name": "Gamlebyen barnehage",
                "no-barnehage:nsrid": "1016090",
                "operator": "Urtehagen Barnehager AS",
                "operator:type": "private",
                "id": "node/-535"
            },
            "geometry": {
                "type": "Point",
                "coordinates": [
                    10.76729,
                    59.90542
                ]
            }
        },
        {
            "type": "Feature",
            "id": "node/-521",
            "properties": {
                "ADDRESS": "Fridtjovs Gate 1, 0658 OSLO",
                "amenity": "kindergarten",
                "capacity": "55",
                "max_age": "5",
                "min_age": "1",
                "name": "Fridtjovsgate barnehage",
                "no-barnehage:nsrid": "1013020",
                "operator": "Oslo kommune",
                "operator:type": "public",
                "id": "node/-521"
            },
            "geometry": {
                "type": "Point",
                "coordinates": [
                    10.79206,
                    59.90709
                ]
            }
        },
        {
            "type": "Feature",
            "id": "node/-497",
            "properties": {
                "ADDRESS": "Etterstadsletta 56, 0659 OSLO",
                "amenity": "kindergarten",
                "capacity": "57",
                "max_age": "5",
                "min_age": "1",
                "name": "Etterstadsletta barnehage",
                "no-barnehage:nsrid": "1013224",
                "operator": "Oslo kommune",
                "operator:type": "public",
                "id": "node/-497"
            },
            "geometry": {
                "type": "Point",
                "coordinates": [
                    10.80528,
                    59.90886
                ]
            }
        },
        {
            "type": "Feature",
            "id": "node/-496",
            "properties": {
                "ADDRESS": "Etterstadsletta 58, 0659 OSLO",
                "amenity": "kindergarten",
                "capacity": "131",
                "max_age": "5",
                "min_age": "1",
                "name": "Etterstadjordet barnehage",
                "no-barnehage:nsrid": "1018611",
                "operator": "Oslo kommune",
                "operator:type": "public",
                "id": "node/-496"
            },
            "geometry": {
                "type": "Point",
                "coordinates": [
                    10.80413,
                    59.90885
                ]
            }
        },
        {
            "type": "Feature",
            "id": "node/-495",
            "properties": {
                "ADDRESS": "Etterstadgata 5, 0658 OSLO",
                "amenity": "kindergarten",
                "capacity": "26",
                "max_age": "5",
                "min_age": "1",
                "name": "Etterstadgata barnehage",
                "no-barnehage:nsrid": "1015620",
                "operator": "Oslo kommune",
                "operator:type": "public",
                "id": "node/-495"
            },
            "geometry": {
                "type": "Point",
                "coordinates": [
                    10.79129,
                    59.90942
                ]
            }
        },
        {
            "type": "Feature",
            "id": "node/-494",
            "properties": {
                "ADDRESS": "Etterstadsletta 45, 0660 OSLO",
                "amenity": "kindergarten",
                "capacity": "125",
                "max_age": "5",
                "min_age": "1",
                "name": "Etterstad barnehage",
                "no-barnehage:nsrid": "1017286",
                "operator": "Oslo kommune",
                "operator:type": "public",
                "id": "node/-494"
            },
            "geometry": {
                "type": "Point",
                "coordinates": [
                    10.80316,
                    59.91034
                ]
            }
        },
        {
            "type": "Feature",
            "id": "node/-479",
            "properties": {
                "ADDRESS": "Ekebergveien 101, 1178 OSLO",
                "amenity": "kindergarten",
                "capacity": "89",
                "max_age": "5",
                "min_age": "1",
                "name": "Ekeberg idrettsbarnehage",
                "no-barnehage:nsrid": "1021409",
                "operator": "Ekeberg Idrettsbarnehage AS",
                "operator:type": "private",
                "id": "node/-479"
            },
            "geometry": {
                "type": "Point",
                "coordinates": [
                    10.77832,
                    59.89164
                ]
            }
        },
        {
            "type": "Feature",
            "id": "node/-478",
            "properties": {
                "ADDRESS": "Arnljot Gellines Vei 5a, 0657 OSLO",
                "amenity": "kindergarten",
                "capacity": "69",
                "max_age": "5",
                "min_age": "1",
                "name": "Eitillstad Fus-barnehage",
                "no-barnehage:nsrid": "1021613",
                "operator": "Eitillstad Fus barnehage AS",
                "operator:type": "private",
                "id": "node/-478"
            },
            "geometry": {
                "type": "Point",
                "coordinates": [
                    10.79384,
                    59.90506
                ]
            }
        },
        {
            "type": "Feature",
            "id": "node/-474",
            "properties": {
                "ADDRESS": "Etterstadsletta 94, 0659 OSLO",
                "amenity": "kindergarten",
                "capacity": "69",
                "contact:website": "http://dumpa.kanvas.no/",
                "max_age": "5",
                "min_age": "1",
                "name": "Dumpa Kanvas-musikkbarnehage",
                "no-barnehage:nsrid": "1025299",
                "operator": "Stiftelsen Kanvas",
                "operator:type": "private",
                "id": "node/-474"
            },
            "geometry": {
                "type": "Point",
                "coordinates": [
                    10.80017,
                    59.90665
                ]
            }
        },
        {
            "type": "Feature",
            "id": "node/-436",
            "properties": {
                "ADDRESS": "Simensbråtveien 25b, 1182 OSLO",
                "amenity": "kindergarten",
                "capacity": "50",
                "max_age": "5",
                "min_age": "1",
                "name": "Brumlebassen barnehage",
                "no-barnehage:nsrid": "1021473",
                "operator": "Brumlebassen barnehage AS",
                "operator:type": "private",
                "id": "node/-436"
            },
            "geometry": {
                "type": "Point",
                "coordinates": [
                    10.79597,
                    59.89897
                ]
            }
        },
        {
            "type": "Feature",
            "id": "node/-404",
            "properties": {
                "ADDRESS": "Bauneveien 47, 1182 OSLO",
                "amenity": "kindergarten",
                "capacity": "103",
                "max_age": "5",
                "min_age": "1",
                "name": "Bauneveien barnehage",
                "no-barnehage:nsrid": "1013820",
                "operator": "Oslo kommune",
                "operator:type": "public",
                "id": "node/-404"
            },
            "geometry": {
                "type": "Point",
                "coordinates": [
                    10.79701,
                    59.89122
                ]
            }
        },
        {
            "type": "Feature",
            "id": "node/-390",
            "properties": {
                "ADDRESS": "Konows Gate 20, 0196 OSLO",
                "amenity": "kindergarten",
                "capacity": "71",
                "max_age": "5",
                "min_age": "1",
                "name": "Baglerbyen FUS barnehage",
                "no-barnehage:nsrid": "1025458",
                "operator": "Baglerbyen Fus barnehage AS",
                "operator:type": "private",
                "id": "node/-390"
            },
            "geometry": {
                "type": "Point",
                "coordinates": [
                    10.77441,
                    59.9029
                ]
            }
        },
        {
            "type": "Feature",
            "id": "node/-366",
            "properties": {
                "ADDRESS": "Vålerenggata 10, 0657 OSLO",
                "amenity": "kindergarten",
                "capacity": "24",
                "max_age": "5",
                "min_age": "1",
                "name": "0 - 6 Vålerenggata barnehage",
                "no-barnehage:nsrid": "1022323",
                "operator": "0 - 6 Vålerenggata barnehage AS",
                "operator:type": "private",
                "id": "node/-366"
            },
            "geometry": {
                "type": "Point",
                "coordinates": [
                    10.78429,
                    59.90791
                ]
            }
        }
    ]
}