{
    "type": "FeatureCollection",
    "features": [
        {
            "type": "Feature",
            "id": "node/-4236",
            "properties": {
                "ADDRESS": "Jernbanegata 19, 2335 STANGE",
                "amenity": "kindergarten",
                "capacity": "124",
                "max_age": "5",
                "min_age": "1",
                "name": "Læringsverkstedet barnehage avd. Nerby",
                "no-barnehage:nsrid": "1015933",
                "operator": "Læringsverkstedet AS",
                "operator:type": "private",
                "id": "node/-4236"
            },
            "geometry": {
                "type": "Point",
                "coordinates": [
                    11.19651,
                    60.71487
                ]
            }
        },
        {
            "type": "Feature",
            "id": "node/-4229",
            "properties": {
                "ADDRESS": "Dragonvegen 15, 2335 STANGE",
                "amenity": "kindergarten",
                "capacity": "49",
                "max_age": "5",
                "min_age": "1",
                "name": "Enerhaugen barnehage",
                "no-barnehage:nsrid": "1017569",
                "operator": "Stange kommune",
                "operator:type": "public",
                "id": "node/-4229"
            },
            "geometry": {
                "type": "Point",
                "coordinates": [
                    11.18457,
                    60.7156
                ]
            }
        }
    ]
}