{
    "type": "FeatureCollection",
    "features": [
        {
            "type": "Feature",
            "id": "node/-225",
            "properties": {
                "amenity": "kindergarten",
                "capacity": "140",
                "doNotImportAddress": "Enerveien 14 1812 ASKIM",
                "max_age": "5",
                "min_age": "1",
                "name": "Trippestadlia barnehage",
                "no-barnehage:nsrid": "1017352",
                "operator": "Askim kommune",
                "operator:type": "public",
                "id": "node/-225"
            },
            "geometry": {
                "type": "Point",
                "coordinates": [
                    11.1903,
                    59.5909
                ]
            }
        },
        {
            "type": "Feature",
            "id": "node/-216",
            "properties": {
                "amenity": "kindergarten",
                "capacity": "124",
                "doNotImportAddress": "Vinkelveien 28 1807 ASKIM",
                "max_age": "5",
                "min_age": "1",
                "name": "Eid barnehage",
                "no-barnehage:nsrid": "2000143",
                "operator": "Askim kommune",
                "operator:type": "public",
                "id": "node/-216"
            },
            "geometry": {
                "type": "Point",
                "coordinates": [
                    11.17982,
                    59.59313
                ]
            }
        },
        {
            "type": "Feature",
            "id": "node/-215",
            "properties": {
                "amenity": "kindergarten",
                "capacity": "22",
                "doNotImportAddress": "Museumsveien 21 1807 ASKIM",
                "max_age": "5",
                "min_age": "1",
                "name": "Askim menighets barnehage",
                "no-barnehage:nsrid": "1016660",
                "operator": "Askim Sokn",
                "operator:type": "private",
                "id": "node/-215"
            },
            "geometry": {
                "type": "Point",
                "coordinates": [
                    11.1766,
                    59.5907
                ]
            }
        },
        {
            "type": "Feature",
            "id": "node/-214",
            "properties": {
                "amenity": "kindergarten",
                "doNotImportAddress": "Vinkelveien 28 1807 ASKIM",
                "name": "Askim kommune åpen barnehage",
                "no-barnehage:nsrid": "1015585",
                "operator": "Askim kommune",
                "operator:type": "public",
                "id": "node/-214"
            },
            "geometry": {
                "type": "Point",
                "coordinates": [
                    11.178,
                    59.5859
                ]
            }
        }
    ]
}