{
    "type": "FeatureCollection",
    "features": [
        {
            "type": "Feature",
            "id": "node/-3460",
            "properties": {
                "amenity": "kindergarten",
                "capacity": "40",
                "contact:email": "postmaster@triobarnehager.no",
                "contact:phone": "+47 74 39 23 10",
                "max_age": "5",
                "min_age": "1",
                "name": "Trio Barnehager AS",
                "no-barnehage:nsrid": "1020387",
                "operator": "Trio Barnehager AS",
                "operator:type": "private",
                "id": "node/-3460"
            },
            "geometry": {
                "type": "Point",
                "coordinates": [
                    11.21553,
                    64.86023
                ]
            }
        },
        {
            "type": "Feature",
            "id": "node/-3456",
            "properties": {
                "amenity": "kindergarten",
                "capacity": "33",
                "contact:email": "heidi@bikubenbarnehage.no",
                "max_age": "5",
                "min_age": "1",
                "name": "Bikuben Friluftsbarnehage AS",
                "no-barnehage:nsrid": "1021593",
                "operator": "Bikuben Friluftsbarnehage AS",
                "operator:type": "private",
                "id": "node/-3456"
            },
            "geometry": {
                "type": "Point",
                "coordinates": [
                    11.23977,
                    64.86705
                ]
            }
        },
        {
            "type": "Feature",
            "id": "node/-3454",
            "properties": {
                "amenity": "kindergarten",
                "capacity": "27",
                "contact:email": "elin.johansen@vikna.kommune.no",
                "max_age": "5",
                "min_age": "1",
                "name": "Austafjord Oppvekstsenter Avdeling Barnehage",
                "no-barnehage:nsrid": "1013859",
                "operator": "Vikna kommune",
                "operator:type": "public",
                "id": "node/-3454"
            },
            "geometry": {
                "type": "Point",
                "coordinates": [
                    11.2373,
                    64.8621
                ]
            }
        }
    ]
}