{
    "type": "FeatureCollection",
    "features": [
        {
            "type": "Feature",
            "id": "node/-5515",
            "properties": {
                "amenity": "kindergarten",
                "capacity": "20",
                "contact:email": "nina@posthornetbarnehage.no",
                "contact:phone": "+47 75 04 18 63",
                "contact:website": "http://www.posthornet.barnehageside.no",
                "max_age": "5",
                "min_age": "1",
                "name": "Posthornet barnehage",
                "no-barnehage:nsrid": "1019839",
                "operator": "Postens Foreldreforening",
                "operator:type": "private",
                "start_date": "1989-01-02",
                "id": "node/-5515"
            },
            "geometry": {
                "type": "Point",
                "coordinates": [
                    12.63146,
                    66.02155
                ]
            }
        }
    ]
}