{
    "type": "FeatureCollection",
    "features": [
        {
            "type": "Feature",
            "id": "node/-5504",
            "properties": {
                "amenity": "kindergarten",
                "capacity": "42",
                "contact:email": "johanne.kjemphei@hemnes.kommune.no",
                "contact:phone": "75197630",
                "max_age": "5",
                "min_age": "1",
                "name": "Bjerka barnehage",
                "no-barnehage:nsrid": "1013660",
                "operator": "Hemnes kommune",
                "operator:type": "public",
                "start_date": "1989-01-01",
                "id": "node/-5504"
            },
            "geometry": {
                "type": "Point",
                "coordinates": [
                    13.8397,
                    66.1455
                ]
            }
        }
    ]
}