{
    "type": "FeatureCollection",
    "features": [
        {
            "type": "Feature",
            "id": "node/-5278",
            "properties": {
                "amenity": "kindergarten",
                "capacity": "39",
                "contact:email": "elin@trollmyra.no",
                "contact:phone": "+47 75 51 82 00",
                "contact:website": "http://www.trollmyra.no",
                "max_age": "5",
                "min_age": "1",
                "name": "Trollmyra barnehage",
                "no-barnehage:nsrid": "1020511",
                "operator": "Trollmyra barnehage AS",
                "operator:type": "private",
                "id": "node/-5278"
            },
            "geometry": {
                "type": "Point",
                "coordinates": [
                    14.57942,
                    67.2904
                ]
            }
        },
        {
            "type": "Feature",
            "id": "node/-5259",
            "properties": {
                "amenity": "kindergarten",
                "capacity": "77",
                "contact:email": "irene.mellemvik@studentinord.no",
                "contact:phone": "+47 75 51 72 40",
                "contact:website": "http://www.studentinord.no",
                "max_age": "5",
                "min_age": "1",
                "name": "Nord Studentsamskipnad avd. Studentongan barnehage",
                "no-barnehage:nsrid": "1015510",
                "operator": "Nord Studentsamskipnad",
                "operator:type": "private",
                "id": "node/-5259"
            },
            "geometry": {
                "type": "Point",
                "coordinates": [
                    14.5644,
                    67.2892
                ]
            }
        },
        {
            "type": "Feature",
            "id": "node/-5256",
            "properties": {
                "amenity": "kindergarten",
                "capacity": "60",
                "contact:email": "anna.lorentzen@bodo.kommune.no",
                "max_age": "5",
                "min_age": "1",
                "name": "Mørkvedmarka barnehage",
                "no-barnehage:nsrid": "1016632",
                "operator": "Bodø kommune",
                "operator:type": "public",
                "id": "node/-5256"
            },
            "geometry": {
                "type": "Point",
                "coordinates": [
                    14.5868,
                    67.2906
                ]
            }
        },
        {
            "type": "Feature",
            "id": "node/-5253",
            "properties": {
                "amenity": "kindergarten",
                "capacity": "74",
                "contact:email": "mellommyra.bhg@norlandiabarnehagene.no",
                "max_age": "5",
                "min_age": "1",
                "name": "Mellommyra barnehage",
                "no-barnehage:nsrid": "1015496",
                "operator": "Norlandia Barnehagene AS",
                "operator:type": "private",
                "id": "node/-5253"
            },
            "geometry": {
                "type": "Point",
                "coordinates": [
                    14.5741,
                    67.2906
                ]
            }
        },
        {
            "type": "Feature",
            "id": "node/-5245",
            "properties": {
                "amenity": "kindergarten",
                "capacity": "39",
                "contact:email": "knerten@laringsverkstedet.no",
                "contact:website": "http://laringsverkstedet.no/barnehage/knerten",
                "max_age": "5",
                "min_age": "1",
                "name": "Læringsverkstedet barnehage avd. Knerten",
                "no-barnehage:nsrid": "1019821",
                "operator": "Læringsverkstedet AS",
                "operator:type": "private",
                "id": "node/-5245"
            },
            "geometry": {
                "type": "Point",
                "coordinates": [
                    14.58696,
                    67.28967
                ]
            }
        },
        {
            "type": "Feature",
            "id": "node/-5239",
            "properties": {
                "amenity": "kindergarten",
                "capacity": "37",
                "contact:email": "kjeldmyrlia.bhg@norlandiabarnehagene.no",
                "max_age": "5",
                "min_age": "1",
                "name": "Kjeldmyrlia barnehage",
                "no-barnehage:nsrid": "1015452",
                "operator": "Norlandia Barnehagene AS",
                "operator:type": "private",
                "id": "node/-5239"
            },
            "geometry": {
                "type": "Point",
                "coordinates": [
                    14.5614,
                    67.2932
                ]
            }
        },
        {
            "type": "Feature",
            "id": "node/-5228",
            "properties": {
                "amenity": "kindergarten",
                "capacity": "103",
                "contact:email": "Bjorneborgen.bhg@norlandiacare.no",
                "max_age": "5",
                "min_age": "1",
                "name": "Bjørneborgen barnehage",
                "no-barnehage:nsrid": "1015464",
                "operator": "Norlandia Barnehagene AS",
                "operator:type": "private",
                "id": "node/-5228"
            },
            "geometry": {
                "type": "Point",
                "coordinates": [
                    14.5887,
                    67.2955
                ]
            }
        }
    ]
}