{
    "type": "FeatureCollection",
    "features": [
        {
            "type": "Feature",
            "id": "node/-5626",
            "properties": {
                "amenity": "kindergarten",
                "capacity": "47",
                "doNotImportAddress": "Toftvegen 10 9017 TROMSØ",
                "max_age": "5",
                "min_age": "1",
                "name": "Toftveien barnehage",
                "no-barnehage:nsrid": "1020105",
                "operator": "Toftveien barnehage Sa",
                "operator:type": "private",
                "id": "node/-5626"
            },
            "geometry": {
                "type": "Point",
                "coordinates": [
                    18.97537,
                    69.69772
                ]
            }
        },
        {
            "type": "Feature",
            "id": "node/-5612",
            "properties": {
                "amenity": "kindergarten",
                "capacity": "67",
                "doNotImportAddress": "Ringvegen 520 9017 TROMSØ",
                "max_age": "5",
                "min_age": "1",
                "name": "Solneset barnehage",
                "no-barnehage:nsrid": "1018441",
                "operator": "Tromsø kommune",
                "operator:type": "public",
                "id": "node/-5612"
            },
            "geometry": {
                "type": "Point",
                "coordinates": [
                    18.9547,
                    69.6961
                ]
            }
        },
        {
            "type": "Feature",
            "id": "node/-5586",
            "properties": {
                "amenity": "kindergarten",
                "capacity": "76",
                "doNotImportAddress": "Valbeinet 1 9017 TROMSØ",
                "max_age": "5",
                "min_age": "1",
                "name": "Kvitungen barnehage",
                "no-barnehage:nsrid": "1015977",
                "operator": "Norlandia Barnehagene AS",
                "operator:type": "private",
                "id": "node/-5586"
            },
            "geometry": {
                "type": "Point",
                "coordinates": [
                    18.9769,
                    69.702
                ]
            }
        }
    ]
}